bladesight-0.16.0.dist-info/METADATA
bladesight-0.16.0.dist-info/WHEEL
bladesight-0.16.0.dist-info/entry_points.txt
bladesight-0.16.0.dist-info/licenses/LICENSE
bladesight/__init__.py
bladesight/btt/__init__.py
bladesight/btt/align.py
bladesight/btt/aoa.py
bladesight/btt/infer/__init__.py
bladesight/btt/infer/cff.py
bladesight/btt/infer/sdof.py
bladesight/btt/triggering_criteria.py
bladesight/btt/zero.py
bladesight/dataset_handler.py
bladesight/ias/__init__.py
bladesight/ias/geometry_compensation.py
bladesight/utils.py
bladesight-0.16.0.dist-info/RECORD
