Metadata-Version: 2.1
Name: bladesight
Version: 0.16.0
Summary: Bladesight provides comprehensive tools for introductory Blade Tip Timing analysis.
Author-Email: Dawie Diamond <dawie.diamond@bladesight.com>
Classifier: Intended Audience :: Science/Research
Classifier: Operating System :: OS Independent
Classifier: Programming Language :: Python :: 3
Classifier: Programming Language :: Python
Classifier: Topic :: Scientific/Engineering
Classifier: Development Status :: 4 - Beta
Classifier: License :: OSI Approved :: MIT License
Classifier: Programming Language :: Python :: 3 :: Only
Classifier: Programming Language :: Python :: 3.9
Classifier: Programming Language :: Python :: 3.10
Classifier: Programming Language :: Python :: 3.11
Classifier: Programming Language :: Python :: 3.12
Project-URL: Homepage, https://www.bladesight.com/
Project-URL: Documentation, https://docs.bladesight.com/
Project-URL: Repository, https://github.com/Bladesight/Bladesight
Requires-Python: <3.13,>=3.9
Requires-Dist: duckdb>=1.0.0
Requires-Dist: numba>=0.57.0
Requires-Dist: pandas>=1.5.1
Requires-Dist: polars>=0.19.2
Requires-Dist: pyarrow>=17.0.0
Requires-Dist: s3fs>=2023.9.0
Requires-Dist: scipy>=1.11.3
Requires-Dist: tqdm>=4.65.0
Requires-Dist: typing-extensions>=4.12.2
Requires-Dist: yaspin>=3.0.1
